fletil/__init__.py
fletil/cli.py
fletil/hot_reload_and_restart.py
fletil/utils.py
fletil-0.3.0.dist-info/entry_points.txt
fletil-0.3.0.dist-info/LICENSE
fletil-0.3.0.dist-info/WHEEL
fletil-0.3.0.dist-info/METADATA
fletil-0.3.0.dist-info/RECORD
