Metadata-Version: 2.1
Name: fletil
Version: 0.3.0
Summary: A CLI for the Flet framework.
Home-page: https://gitlab.com/skeledrew/fletil
License: MIT
Keywords: flet,cli
Author: Andrew Phillips
Author-email: skeledrew@gmail.com
Requires-Python: >=3.10,<4.0
Classifier: Development Status :: 4 - Beta
Classifier: Environment :: Console
Classifier: Intended Audience :: Developers
Classifier: License :: OSI Approved :: MIT License
Classifier: Programming Language :: Python :: 3
Classifier: Programming Language :: Python :: 3.10
Classifier: Topic :: Software Development
Classifier: Topic :: Utilities
Requires-Dist: fire (>=0.4.0,<0.5.0)
Requires-Dist: flet (>=0.1.52,<0.2.0)
Requires-Dist: loguru (>=0.6.0,<0.7.0)
Requires-Dist: watchdog (>=2.1.9,<3.0.0)
Project-URL: Repository, https://gitlab.com/skeledrew/fletil
